[
	{
		"time": 1547277582994,
		"file": "2019-01-12-15-19-42.zip",
		"index": 14,
		"success": true,
		"size": 3686645
	},
	{
		"time": 1549439655986,
		"file": "2019-02-06-15-54-15.zip",
		"index": 15,
		"success": true,
		"size": 10459536
	},
	{
		"time": 1549535909661,
		"file": "2019-02-07-18-38-29.zip",
		"index": 16,
		"success": true,
		"size": 55250609
	},
	{
		"time": 1549617006820,
		"file": "2019-02-08-17-10-06.zip",
		"index": 17,
		"success": true,
		"size": 59045967
	},
	{
		"time": 1549790529151,
		"file": "2019-02-10-17-22-09.zip",
		"index": 18,
		"success": true,
		"size": 53117202
	},
	{
		"time": 1550311060613,
		"file": "2019-02-16-17-57-40.zip",
		"index": 19,
		"success": true,
		"size": 62177266
	},
	{
		"time": 1555148420629,
		"file": "2019-04-13-17-40-20.zip",
		"index": 20,
		"success": true,
		"size": 33984601
	},
	{
		"time": 1555155620564,
		"file": "2019-04-13-19-40-20.zip",
		"index": 21,
		"success": true,
		"size": 34178825
	},
	{
		"time": 1555227391390,
		"file": "2019-04-14-15-36-31.zip",
		"index": 22,
		"success": true,
		"size": 42522932
	},
	{
		"time": 1555234853095,
		"file": "2019-04-14-17-40-53.zip",
		"index": 23,
		"success": true,
		"size": 42534946
	},
	{
		"time": 1555242084465,
		"file": "2019-04-14-19-41-24.zip",
		"index": 24,
		"success": true,
		"size": 42536045
	},
	{
		"time": 1555501104069,
		"file": "2019-04-17-19-38-24.zip",
		"index": 25,
		"success": true,
		"size": 42536679
	}
]