{
  "pools": [
    {
      "name": "materials",
      "entries": [
        {
          "entryName": "minecraft:emerald",
          "weight": 1,
          "quality": 0,
          "type": "item",
          "functions": [
            {
              "count": 1.0,
              "function": "minecraft:set_count"
            }
          ],
          "name": "minecraft:emerald"
        },
        {
          "entryName": "minecraft:diamond",
          "weight": 1,
          "quality": 0,
          "type": "item",
          "functions": [
            {
              "count": 1.0,
              "function": "minecraft:set_count"
            }
          ],
          "name": "minecraft:diamond"
        },
        {
          "entryName": "bewitchment:juniper_sapling",
          "weight": 1,
          "quality": 0,
          "type": "item",
          "functions": [
            {
              "count": {
                "min": 0.0,
                "max": 2.0
              },
              "function": "minecraft:set_count"
            }
          ],
          "name": "bewitchment:juniper_sapling"
        },
        {
          "entryName": "bewitchment:salt",
          "weight": 1,
          "quality": 0,
          "type": "item",
          "functions": [
            {
              "count": {
                "min": 0.0,
                "max": 16.0
              },
              "function": "minecraft:set_count"
            }
          ],
          "name": "bewitchment:salt"
        },
        {
          "entryName": "bewitchment:elder_sapling",
          "weight": 1,
          "quality": 0,
          "type": "item",
          "functions": [
            {
              "count": {
                "min": 0.0,
                "max": 2.0
              },
              "function": "minecraft:set_count"
            }
          ],
          "name": "bewitchment:elder_sapling"
        },
        {
          "entryName": "bewitchment:cypress_sapling",
          "weight": 1,
          "quality": 0,
          "type": "item",
          "functions": [
            {
              "count": {
                "min": 0.0,
                "max": 2.0
              },
              "function": "minecraft:set_count"
            }
          ],
          "name": "bewitchment:cypress_sapling"
        },
        {
          "entryName": "minecraft:gold_ingot",
          "weight": 2,
          "quality": 0,
          "type": "item",
          "functions": [
            {
              "count": {
                "min": 1.0,
                "max": 2.0
              },
              "function": "minecraft:set_count"
            }
          ],
          "name": "minecraft:gold_ingot"
        },
        {
          "entryName": "bewitchment:silver_ingot",
          "weight": 1,
          "quality": 0,
          "type": "item",
          "functions": [
            {
              "count": {
                "min": 1.0,
                "max": 2.0
              },
              "function": "minecraft:set_count"
            }
          ],
          "name": "bewitchment:silver_ingot"
        },
        {
          "entryName": "bewitchment:amethyst",
          "weight": 8,
          "quality": 0,
          "type": "item",
          "functions": [
            {
              "count": {
                "min": 0.0,
                "max": 3.0
              },
              "function": "minecraft:set_count"
            }
          ],
          "name": "bewitchment:amethyst"
        },
        {
          "entryName": "bewitchment:garnet",
          "weight": 8,
          "quality": 0,
          "type": "item",
          "functions": [
            {
              "count": {
                "min": 0.0,
                "max": 3.0
              },
              "function": "minecraft:set_count"
            }
          ],
          "name": "bewitchment:garnet"
        },
        {
          "entryName": "bewitchment:opal",
          "weight": 8,
          "quality": 0,
          "type": "item",
          "functions": [
            {
              "count": {
                "min": 0.0,
                "max": 3.0
              },
              "function": "minecraft:set_count"
            }
          ],
          "name": "bewitchment:opal"
        },
        {
          "entryName": "bewitchment:fortunes_favor",
          "weight": 2,
          "quality": 0,
          "type": "item",
          "functions": [
            {
              "count": {
                "min": 0.0,
                "max": 1.0
              },
              "function": "minecraft:set_count"
            }
          ],
          "name": "bewitchment:fortunes_favor"
        },
        {
          "entryName": "bewitchment:hecates_visage",
          "weight": 1,
          "quality": 0,
          "type": "item",
          "functions": [
            {
              "count": {
                "min": 0.0,
                "max": 1.0
              },
              "function": "minecraft:set_count"
            }
          ],
          "name": "bewitchment:hecates_visage"
        },
        {
          "entryName": "bewitchment:triskelion",
          "weight": 1,
          "quality": 0,
          "type": "item",
          "functions": [
            {
              "count": {
                "min": 0.0,
                "max": 1.0
              },
              "function": "minecraft:set_count"
            }
          ],
          "name": "bewitchment:triskelion"
        }
      ],
      "rolls": 2.0
    }
  ]
}