{
  "pools": [
    {
      "name": "pool1",
      "entries": [
        {
          "entryName": "minecraft:fish",
          "weight": 1,
          "quality": 0,
          "conditions": [
            {
              "chance": 0.5,
              "looting_multiplier": 0.1,
              "condition": "minecraft:random_chance_with_looting"
            }
          ],
          "type": "item",
          "functions": [
            {
              "count": {
                "min": 0.0,
                "max": 2.0
              },
              "function": "minecraft:set_count"
            },
            {
              "count": {
                "min": 1.0,
                "max": 2.0
              },
              "function": "minecraft:looting_enchant"
            },
            {
              "tag": "{}",
              "function": "minecraft:set_nbt"
            }
          ],
          "name": "minecraft:fish"
        }
      ],
      "rolls": 1.0
    },
    {
      "name": "pool2",
      "entries": [
        {
          "entryName": "minecraft:fish",
          "weight": 1,
          "quality": 0,
          "conditions": [
            {
              "chance": 0.5,
              "looting_multiplier": 0.1,
              "condition": "minecraft:random_chance_with_looting"
            }
          ],
          "type": "item",
          "functions": [
            {
              "count": 1.0,
              "function": "minecraft:set_count"
            },
            {
              "count": 1.0,
              "function": "minecraft:looting_enchant"
            },
            {
              "data": 1.0,
              "function": "minecraft:set_data"
            },
            {
              "tag": "{}",
              "function": "minecraft:set_nbt"
            }
          ],
          "name": "minecraft:fish"
        }
      ],
      "rolls": 1.0
    },
    {
      "name": "pool3",
      "entries": [
        {
          "entryName": "avatarmod:scroll",
          "weight": 1,
          "quality": 0,
          "conditions": [
            {
              "chance": 0.12,
              "looting_multiplier": 0.05,
              "condition": "minecraft:random_chance_with_looting"
            }
          ],
          "type": "item",
          "functions": [
            {
              "count": 1.0,
              "function": "minecraft:set_count"
            },
            {
              "count": 1.0,
              "function": "minecraft:looting_enchant"
            },
            {
              "data": 3.0,
              "function": "minecraft:set_data"
            },
            {
              "tag": "{}",
              "function": "minecraft:set_nbt"
            }
          ],
          "name": "avatarmod:scroll"
        }
      ],
      "rolls": 1.0
    }
  ]
}